gtm_rosamii1/__init__.py
gtm_rosamii1/__main__.py
gtm_rosamii1/emails_notepad.txt
gtm_rosamii1/gen_research.md
gtm_rosamii1/gtm_agent.py
gtm_rosamii1/gtm_prompt.md
gtm_rosamii1/inv_research_prompt.md
gtm_rosamii1/llm_util.py
gtm_rosamii1/main.py
gtm_rosamii1/sample_placeholder.md
gtm_rosamii1/samples.py
gtm_rosamii1/simple_agent.py
gtm_rosamii1/util.py
gtm_rosamii1-1.2.13.dist-info/licenses/LICENSE.txt
gtm_rosamii1-1.2.13.dist-info/METADATA
gtm_rosamii1-1.2.13.dist-info/WHEEL
gtm_rosamii1-1.2.13.dist-info/top_level.txt
gtm_rosamii1-1.2.13.dist-info/RECORD
