Metadata-Version: 2.4
Name: gtm_rosamii1
Version: 1.2.13
Summary: GTM Agent for Generating Emails
Author-email: Roshan Sami <roshan.sami@onepint.ai>
License-Expression: MIT
Project-URL: Homepage, https://https://github.com/onepintai/opllm-generic-agents/tree/gtm-roshan
Classifier: Programming Language :: Python :: 3
Classifier: Operating System :: OS Independent
Requires-Python: >=3.13
License-File: LICENSE.txt
Requires-Dist: fastmcp>=2.11.3
Requires-Dist: httpx>=0.28.1
Requires-Dist: langchain-core>=0.3.0
Requires-Dist: langchain==0.3.20
Requires-Dist: langchain-tavily>=0.2.11
Requires-Dist: langgraph>=0.2.4
Requires-Dist: langgraph-checkpoint==1.0.12
Requires-Dist: langchain-openai>=0.1.23
Requires-Dist: langgraph-checkpoint-postgres==1.0.0
Requires-Dist: mcp[cli]>=1.13.0
Requires-Dist: numpy>=1.26.4
Requires-Dist: openpyxl>=3.1.5
Requires-Dist: pandas>=2.3.2
Requires-Dist: psycopg>=3.2.9
Requires-Dist: psycopg-pool>=3.2.6
Requires-Dist: pydantic>=2.11.7
Requires-Dist: tavily-python>=0.7.11
Dynamic: license-file
